CHANGELOG.md
README.md
sample_size/__init__.py
sample_size/metrics.py
sample_size/metrics_schema.json
sample_size/multiple_testing.py
sample_size/sample_size_calculator.py
sample_size/scripts/__init__.py
sample_size/scripts/input_utils.py
sample_size/scripts/sample_size_run.py
sample_size-3.0.0.dist-info/entry_points.txt
sample_size-3.0.0.dist-info/LICENSE
sample_size-3.0.0.dist-info/WHEEL
sample_size-3.0.0.dist-info/METADATA
sample_size-3.0.0.dist-info/RECORD
