Metadata-Version: 2.1
Name: sample-size
Version: 3.0.0
Summary: A python module implementing power analysis to estimate sample size
Keywords: sample size,experimentation,power analysis
Maintainer: GoDaddy
Maintainer-email: oss@godaddy.com
Requires-Python: >=3.7.1,<3.11
Classifier: Programming Language :: Python :: 3
Classifier: Programming Language :: Python :: 3.8
Classifier: Programming Language :: Python :: 3.9
Classifier: Programming Language :: Python :: 3.10
Requires-Dist: jsonschema (>=4.5.1,<5.0.0)
Requires-Dist: statsmodels (>=0.13.1,<0.14.0)
